MIPS/Testbenches/ALU32bit.v
`timescale 1ns/1ns
/* 
ALU Module - takes the opcode, contents of the registers, shiftAmount, ALUResult and AluSrc signals, with the signedImm as arguments
*/

module ALU32bit(ALU_result, branch_sig, opcode, rs_value, rt_value, shamt, funct, imm);
	
    input [5:0] funct, opcode;
    input [4:0] shamt; // shift amount
    input [15:0] imm;
    input [31:0] rs_value, rt_value; //inputs
    output reg branch_sig;
    output reg [31:0] ALU_result; //Output of the ALU
	
    integer i; //Loop counter
    // Temporary variable - temp for SRA - Shift Right Arithmetic
    reg signed [31:0] temp, signed_rs, signed_rt; 
    reg [31:0] signExtend, zeroExtend;

    always @ (funct, rs_value, rt_value, shamt, imm) begin
		
		
        // Signed value assignment
        signed_rs = rs_value;
        signed_rt = rt_value;
			
			
        // R-type instruction
        if(opcode == 6'h0) begin
			
            case(funct)
			
                6'h20 : //ADD
                    ALU_result = signed_rs + signed_rt;
				
                6'h21 : //ADDU - Add unsigned
                    ALU_result = rs_value + rt_value;
					
                6'h22 : //SUB - Subtract
                    ALU_result = signed_rs - signed_rt;
					
                6'h23 : //SUBU - Subtract unsigned
                    ALU_result = rs_value - rt_value;
					
                6'h24 : //AND
                    ALU_result = rs_value & rt_value;
					
                6'h25 : //OR
                    ALU_result = rs_value | rt_value;
					
                6'h27 : //NOR
                    ALU_result = ~(rs_value | rt_value);
					
                6'h03 : //SRA (Shift Right Arithmetic - An arithmetic right shift replicates the sign bit as needed to fill bit positions)
                    begin
                        temp = rt_value;
                        for(i = 0; i < shamt; i = i + 1) begin
                            temp = {temp[31],temp[31:1]}; //add the lsb for msb
                        end
					
                    ALU_result = temp;
                    end
					
                6'h02 : //SRL - Shift Right Logical >>
                    ALU_result = (rt_value >> shamt);
			
                6'h00 : //SLL - Shift Left Logical <<
                    ALU_result = (rt_value << shamt);
				
                6'h2b : //SLTU - Set less than unsigned
                    begin
                        if(rs_value < rt_value) begin
                            ALU_result = 1;
                        end else begin
                            ALU_result = 0;
                        end
                    end
					
                6'h2a : //SLT - Set less than
                    begin
                        if(signed_rs < signed_rt) begin
                            ALU_result = 1;
                        end else begin
                            ALU_result = 0;
                        end
                    end
			
            endcase
			
        end 
		
		
		
        // I type
        else begin
			
            signExtend = {{16{imm[15]}}, imm};
            zeroExtend = {{16{1'b0}}, imm};
			
            case(opcode)
		
                6'h8 : // ADDI - Add Immediate
                    ALU_result = signed_rs + signExtend;
					
                6'h9 : // ADDIU - Add Immediate unsigned
                    ALU_result = rs_value + signExtend;
					
                6'b010010 : // ANDI - And Immediate
                    ALU_result = rs_value & zeroExtend;
					
                6'h4 : // BEQ - Branch on Equal
                    begin
                        ALU_result = signed_rs - signed_rt;
                        if(ALU_result == 0) begin
                            branch_sig = 1'b1;
                        end
                        else begin
                            branch_sig = 1'b0;
                        end
                    end
				
                6'h5 : // BNE - Branch not equal
                    begin
                        ALU_result = signed_rs - signed_rt;
                        if(ALU_result != 0) begin
                            branch_sig = 1'b1;
                            ALU_result = 1'b0;
                        end
                        else begin
                            branch_sig = 1'b0;
                        end
                    end
				
                6'b010101 : // LUI - Load upper imm
                    ALU_result = {imm, {16{1'b0}}};
				
                6'b010011 : // ORI - Or Immediate
                    ALU_result = rs_value | zeroExtend;
				
                6'b001010 : // SLTI - Set less than imm
                    begin
                        if(signed_rs < $signed(signExtend)) begin
                            ALU_result = 1;
                        end else begin
                            ALU_result = 0;
                        end
                    end
				
                6'b001011 : // SLTIU - Set less than imm unsigned
                    begin
                        if(rs_value < signExtend) begin
                            ALU_result = 1;
                        end else begin
                            ALU_result = 0;
                        end
                    end
                6'h28 : // SB - Store byte
                    ALU_result = signed_rs + signExtend;
                6'h29 : // SH -Store halfword
                    ALU_result = signed_rs + signExtend;
                6'h2b : // SW - Store Word
                    ALU_result = signed_rs + signExtend;
                6'h23 : // LW - Load Word
                    ALU_result = signed_rs + signExtend;
                6'h24 : // LBU - Load 
                    ALU_result = signed_rs + signExtend;
                6'h25 : // LHU - Load halfword unsigned
                    ALU_result = signed_rs + signExtend;
                6'h30 : // LL - Load linked
                    ALU_result = signed_rs + signExtend;
				
            endcase
		
        end
		
    end
	
	
    initial 
    begin
        $monitor("Opcode : %6b, RS : %32b, RT : %32b, signExtendImm = %32b, Result : %32b\n",
        opcode, rs_value, rt_value, signExtend, ALU_result);
    end
	
endmodule

module alu32bittb();
    reg [5:0] funct, opcode;
    reg [4:0] shamt; // shift amount
    reg [15:0] imm;
    reg [31:0] rs_value, rt_value; //inputs
    wire branch_sig;
    wire [31:0] ALU_result; //Output of the ALU


    ALU32bit testerboi(.ALU_result(ALU_result),
             .branch_sig(branch_sig),
             .opcode(opcode),
             .rs_value(rs_value),
             .rt_value(rt_value),
             .shamt(shamt),
             .funct(funct),
             .imm(imm));

    initial begin
        opcode = 6'h0;
        
        //Add 12 and -10
        rs_value = 12;
        rt_value = -10;
        funct = 6'h20;
        shamt = 0;
        imm = 20;
        #10;

        //Subtract 3 from 1
        rs_value = 1;
        rt_value = 3;
        funct = 6'h22;
        shamt = 0;
        imm = 20;
        #10;

        //Shift 13 twice to left
        rs_value = 0;
        rt_value = 13;
        funct = 6'h00;
        shamt = 2;
        imm = 20;
        #10;
        
        //Add 15 to 1500 from imm field
        opcode = 6'h8;
        rs_value = 15;
        rt_value = 0;
        imm = 1500;
        #10;
        
        //Or Imm of 7 and 1024 from imm
        opcode = 6'b010011;
        rs_value = 7;
        rt_value = 0;
        imm = 1024;
        #10;

        //generate address for load word
        opcode = 6'h23;
        rs_value = -8;
        rt_value = 0;
        imm = 1024;
        #10;

        //signal on beq
        opcode = 6'h4;
        rs_value = 4;
        rt_value = 4;
        imm = 1024;
        #10;

        //signal on beq
        opcode = 6'h4;
        rs_value = 4;
        rt_value = 5;
        imm = 1024;
        #10;

    end

    initial begin
        $dumpfile("ALU32Bittb.vcd"); 
        $dumpvars(0, alu32bittb);
    end

endmodule

MIPS/Testbenches/ALU32Bittb.vcd
$date
	Sun Jun 14 08:46:02 2020
$end
$version
	Icarus Verilog
$end
$timescale
	1ns
$end
$scope module alu32bittb $end
$var wire 1 ! branch_sig $end
$var wire 32 " ALU_result [31:0] $end
$var reg 6 # funct [5:0] $end
$var reg 16 $ imm [15:0] $end
$var reg 6 % opcode [5:0] $end
$var reg 32 & rs_value [31:0] $end
$var reg 32 ' rt_value [31:0] $end
$var reg 5 ( shamt [4:0] $end
$scope module testerboi $end
$var wire 6 ) funct [5:0] $end
$var wire 16 * imm [15:0] $end
$var wire 6 + opcode [5:0] $end
$var wire 32 , rs_value [31:0] $end
$var wire 32 - rt_value [31:0] $end
$var wire 5 . shamt [4:0] $end
$var reg 32 / ALU_result [31:0] $end
$var reg 1 ! branch_sig $end
$var reg 32 0 signExtend [31:0] $end
$var reg 32 1 signed_rs [31:0] $end
$var reg 32 2 signed_rt [31:0] $end
$var reg 32 3 temp [31:0] $end
$var reg 32 4 zeroExtend [31:0] $end
$var integer 32 5 i [31:0] $end
$upscope $end
$upscope $end
$enddefinitions $end
#0
$dumpvars
bx 5
bx 4
bx 3
b11111111111111111111111111110110 2
b1100 1
bx 0
b10 /
b0 .
b11111111111111111111111111110110 -
b1100 ,
b0 +
b10100 *
b100000 )
b0 (
b11111111111111111111111111110110 '
b1100 &
b0 %
b10100 $
b100000 #
b10 "
x!
$end
#10
b11111111111111111111111111111110 "
b11111111111111111111111111111110 /
b11 2
b1 1
b100010 #
b100010 )
b11 '
b11 -
b1 &
b1 ,
#20
b110100 "
b110100 /
b1101 2
b0 1
b10 (
b10 .
b0 #
b0 )
b1101 '
b1101 -
b0 &
b0 ,
#30
b10111101011 "
b10111101011 /
b10111011100 4
b10111011100 0
b0 2
b1111 1
b10111011100 $
b10111011100 *
b0 '
b0 -
b1111 &
b1111 ,
b1000 %
b1000 +
#40
b10000000111 "
b10000000111 /
b10000000000 4
b10000000000 0
b111 1
b10000000000 $
b10000000000 *
b111 &
b111 ,
b10011 %
b10011 +
#50
b1111111000 "
b1111111000 /
b11111111111111111111111111111000 1
b11111111111111111111111111111000 &
b11111111111111111111111111111000 ,
b100011 %
b100011 +
#60
1!
b0 "
b0 /
b100 2
b100 1
b100 '
b100 -
b100 &
b100 ,
b100 %
b100 +
#70
0!
b11111111111111111111111111111111 "
b11111111111111111111111111111111 /
b101 2
b101 '
b101 -
