MIPS/Code/ALU32bit.v
`timescale 1ns/1ns
/* Module designed to act as the ALU - takes in the opcode, contents of the registers, shiftAmount, ALUResult and AluSrc signals
   with the signedImm as arguments
*/

module ALU32bit(ALU_result, sig_branch, opcode, rs_content, rt_content, shamt, funct, immediate);
	
    input [5:0] funct, opcode;
    input [4:0] shamt; // shift amount
    input [15:0] immediate;
    input [31:0] rs_content, rt_content; //inputs
    output reg sig_branch;
    output reg [31:0] ALU_result; //Output of the ALU
	
    integer i; //Loop counter
    // Temporary variable - temp for SRA - Shift Right Arithmetic
    reg signed [31:0] temp, signed_rs, signed_rt; 
    reg [31:0] signExtend, zeroExtend;

    always @ (funct, rs_content, rt_content, shamt, immediate) begin
		
		
        // Signed value assignment
        signed_rs = rs_content;
        signed_rt = rt_content;
			
			
        // R-type instruction
        if(opcode == 6'h0) begin
			
            case(funct)
			
                6'h20 : //ADD
                    ALU_result = signed_rs + signed_rt;
				
                6'h21 : //ADDU - Add unsigned
                    ALU_result = rs_content + rt_content;
					
                6'h22 : //SUB - Subtract
                    ALU_result = signed_rs - signed_rt;
					
                6'h23 : //SUBU - Subtract unsigned
                    ALU_result = rs_content - rt_content;
					
                6'h24 : //AND
                    ALU_result = rs_content & rt_content;
					
                6'h25 : //OR
                    ALU_result = rs_content | rt_content;
					
                6'h27 : //NOR
                    ALU_result = ~(rs_content | rt_content);
					
                6'h03 : //SRA (Shift Right Arithmetic - An arithmetic right shift replicates the sign bit as needed to fill bit positions)
                    begin
                        temp = rt_content;
                        for(i = 0; i < shamt; i = i + 1) begin
                            temp = {temp[31],temp[31:1]}; //add the lsb for msb
                        end
					
                    ALU_result = temp;
                    end
					
                6'h02 : //SRL - Shift Right Logical >>
                    ALU_result = (rt_content >> shamt);
			
                6'h00 : //SLL - Shift Left Logical <<
                    ALU_result = (rt_content << shamt);
				
                6'h2b : //SLTU - Set less than unsigned
                    begin
                        if(rs_content < rt_content) begin
                            ALU_result = 1;
                        end else begin
                            ALU_result = 0;
                        end
                    end
					
                6'h2a : //SLT - Set less than
                    begin
                        if(signed_rs < signed_rt) begin
                            ALU_result = 1;
                        end else begin
                            ALU_result = 0;
                        end
                    end
			
            endcase
			
        end 
		
		
		
        // I type
        else begin
			
            signExtend = {{16{immediate[15]}}, immediate};
            zeroExtend = {{16{1'b0}}, immediate};
			
            case(opcode)
		
                6'h8 : // ADDI - Add Immediate
                    ALU_result = signed_rs + signExtend;
					
                6'h9 : // ADDIU - Add Immediate unsigned
                    ALU_result = rs_content + signExtend;
					
                6'b010010 : // ANDI - And Immediate
                    ALU_result = rs_content & zeroExtend;
					
                6'h4 : // BEQ - Branch on Equal
                    begin
                        ALU_result = signed_rs - signed_rt;
                        if(ALU_result == 0) begin
                            sig_branch = 1'b1;
                        end
                        else begin
                            sig_branch = 1'b0;
                        end
                    end
				
                6'h5 : // BNE - Branch not equal
                    begin
                        ALU_result = signed_rs - signed_rt;
                        if(ALU_result != 0) begin
                            sig_branch = 1'b1;
                            ALU_result = 1'b0;
                        end
                        else begin
                            sig_branch = 1'b0;
                        end
                    end
				
                6'b010101 : // LUI - Load upper immediate
                    ALU_result = {immediate, {16{1'b0}}};
				
                6'b010011 : // ORI - Or Immediate
                    ALU_result = rs_content | zeroExtend;
				
                6'b001010 : // SLTI - Set less than immediate
                    begin
                        if(signed_rs < $signed(signExtend)) begin
                            ALU_result = 1;
                        end else begin
                            ALU_result = 0;
                        end
                    end
				
                6'b001011 : // SLTIU - Set less than immediate unsigned
                    begin
                        if(rs_content < signExtend) begin
                            ALU_result = 1;
                        end else begin
                            ALU_result = 0;
                        end
                    end
                6'h28 : // SB - Store byte
                    ALU_result = signed_rs + signExtend;
                6'h29 : // SH -Store halfword
                    ALU_result = signed_rs + signExtend;
                6'h2b : // SW - Store Word
                    ALU_result = signed_rs + signExtend;
                6'h23 : // LW - Load Word
                    ALU_result = signed_rs + signExtend;
                6'h24 : // LBU - Load 
                    ALU_result = signed_rs + signExtend;
                6'h25 : // LHU - Load halfword unsigned
                    ALU_result = signed_rs + signExtend;
                6'h30 : // LL - Load linked
                    ALU_result = signed_rs + signExtend;
				
            endcase
		
        end
		
    end
	
	
    initial 
    begin
        $monitor("Opcode : %6b, RS : %32b, RT : %32b, signExtendImm = %32b, Result : %32b\n",
        opcode, rs_content, rt_content, signExtend, ALU_result);
    end
	
endmodule

module alu32bittb();
    reg [5:0] funct, opcode;
    reg [4:0] shamt; // shift amount
    reg [15:0] immediate;
    reg [31:0] rs_content, rt_content; //inputs
    wire sig_branch;
    wire [31:0] ALU_result; //Output of the ALU


    ALU32bit testerboi(.ALU_result(ALU_result),
             .sig_branch(sig_branch),
             .opcode(opcode),
             .rs_content(rs_content),
             .rt_content(rt_content),
             .shamt(shamt),
             .funct(funct),
             .immediate(immediate));

    initial begin
        opcode = 6'h0;
        
        //Add 12 and -10
        rs_content = 12;
        rt_content = -10;
        funct = 6'h20;
        shamt = 0;
        immediate = 20;
        #10;

        //Subtract 3 from 1
        rs_content = 1;
        rt_content = 3;
        funct = 6'h22;
        shamt = 0;
        immediate = 20;
        #10;

        //Shift 13 twice to left
        rs_content = 0;
        rt_content = 13;
        funct = 6'h00;
        shamt = 2;
        immediate = 20;
        #10;
        
        //Shift 5 to 1500 from imm field
        opcode = 6'h8;
        rs_content = 15;
        rt_content = 0;
        immediate = 1500;
        #10;
        
        //Or Imm of 7 and 1024 from imm
        opcode = 6'b010011;
        rs_content = 7;
        rt_content = 0;
        immediate = 1024;
        #10;

        //generate address for load word
        opcode = 6'h23;
        rs_content = -8;
        rt_content = 0;
        immediate = 1024;
        #10;

        //signal on beq
        opcode = 6'h4;
        rs_content = 4;
        rt_content = 4;
        immediate = 1024;
        #10;

        //signal on beq
        opcode = 6'h4;
        rs_content = 4;
        rt_content = 5;
        immediate = 1024;
        #10;

    end

    initial begin
        $dumpfile("ALU32Bittb.vcd"); 
        $dumpvars(0, alu32bittb);
    end

endmodule

MIPS/VCD Files/ALU32Bittb.vcd
$date
	Fri Jun 12 17:12:24 2020
$end
$version
	Icarus Verilog
$end
$timescale
	1ns
$end
$scope module alu32bittb $end
$var wire 1 ! sig_branch $end
$var wire 32 " ALU_result [31:0] $end
$var reg 6 # funct [5:0] $end
$var reg 16 $ immediate [15:0] $end
$var reg 6 % opcode [5:0] $end
$var reg 32 & rs_content [31:0] $end
$var reg 32 ' rt_content [31:0] $end
$var reg 5 ( shamt [4:0] $end
$scope module testerboi $end
$var wire 6 ) funct [5:0] $end
$var wire 16 * immediate [15:0] $end
$var wire 6 + opcode [5:0] $end
$var wire 32 , rs_content [31:0] $end
$var wire 32 - rt_content [31:0] $end
$var wire 5 . shamt [4:0] $end
$var reg 32 / ALU_result [31:0] $end
$var reg 1 ! sig_branch $end
$var reg 32 0 signExtend [31:0] $end
$var reg 32 1 signed_rs [31:0] $end
$var reg 32 2 signed_rt [31:0] $end
$var reg 32 3 temp [31:0] $end
$var reg 32 4 zeroExtend [31:0] $end
$var integer 32 5 i [31:0] $end
$upscope $end
$upscope $end
$enddefinitions $end
#0
$dumpvars
bx 5
bx 4
bx 3
b11111111111111111111111111110110 2
b1100 1
bx 0
b10 /
b0 .
b11111111111111111111111111110110 -
b1100 ,
b0 +
b10100 *
b100000 )
b0 (
b11111111111111111111111111110110 '
b1100 &
b0 %
b10100 $
b100000 #
b10 "
x!
$end
#10
b11111111111111111111111111111110 "
b11111111111111111111111111111110 /
b11 2
b1 1
b100010 #
b100010 )
b11 '
b11 -
b1 &
b1 ,
#20
b110100 "
b110100 /
b1101 2
b0 1
b10 (
b10 .
b0 #
b0 )
b1101 '
b1101 -
b0 &
b0 ,
#30
b10111101011 "
b10111101011 /
b10111011100 4
b10111011100 0
b0 2
b1111 1
b10111011100 $
b10111011100 *
b0 '
b0 -
b1111 &
b1111 ,
b1000 %
b1000 +
#40
b10000000111 "
b10000000111 /
b10000000000 4
b10000000000 0
b111 1
b10000000000 $
b10000000000 *
b111 &
b111 ,
b10011 %
b10011 +
#50
b1111111000 "
b1111111000 /
b11111111111111111111111111111000 1
b11111111111111111111111111111000 &
b11111111111111111111111111111000 ,
b100011 %
b100011 +
#60
1!
b0 "
b0 /
b100 2
b100 1
b100 '
b100 -
b100 &
b100 ,
b100 %
b100 +
#70
0!
b11111111111111111111111111111111 "
b11111111111111111111111111111111 /
b101 2
b101 '
b101 -
