uPower/Code/Read_Registers.v
/* Module to read the 64-bit registers and read/write according to the RegWrite an RegRead signals*/

module read_registers(
    output reg [63:0] read_data_1, read_data_2, // The output are two 64-bit binary numbers that contain the data stored in RS and RT
    input [63:0] write_data, // The output are two 32-bit binary numbers that contain the data stored in RS and RT
    input [4:0] rs, rt, rd,  // RS and RT are the read registers and RD (Destination register) is the write register
    input [5:0] opcode,  // 6 bit opcode
    input RegRead, RegWrite, RegDst, clk  // RegRead and RegWrite are signals that indicate whether the instruction needs to read from registers and/or write to a register
);

    reg [63:0] registers [31:0];  //The set of 64 bit registers

    initial 
    begin
        $readmemb("registers.mem", registers);  //Reads all the values stored in the 32 registers
    end

    always @(write_data)
    begin
        if(RegWrite)
        begin
            /* RegWrite = 0 => Write to RT
               RegWrite = 1 => Write to RD    */
            if (RegDst)
            begin
                if(opcode == 6'd34)     //Load Byte
                    registers[rd] = {{56{1'b0}}, write_data[7:0]};
                else if (opcode == 6'd40)       //Load halfword and Zero
                    registers[rd] = {{48{1'b0}}, write_data[15:0]};
                else if (opcode == 6'd42)       //Load halfword with sign extension
                    registers[rd] = {{48{write_data[15]}}, write_data[15:0]};
                else if(opcode == 6'd32)        //Load word
                    registers[rd] = {{32{1'b0}}, write_data[31:0]};
                else                            //Load doubleword
                    registers[rd] = write_data;
            end
            else
            begin
                if(opcode == 6'd34)             //Load byte
                    registers[rt] = {{56{1'b0}}, write_data[7:0]};
                else if (opcode == 6'd40)       //Load halfword and zero
                    registers[rt] = {{48{1'b0}}, write_data[15:0]};
                else if (opcode == 6'd42)       //Load halfword with sign extension
                    registers[rt] = {{48{write_data[15]}}, write_data[15:0]};
                else if(opcode == 6'd32)        //Load word
                    registers[rt] = {{32{1'b0}}, write_data[31:0]};
                else                            //Load doubleword
                    registers[rt] = write_data;
            end
            //Write back the values in the registers file
            $writememb("registers.mem", registers);
        end
    end
    
    always @(read_data_1, read_data_2)
    begin
        //Read from registers
        if(RegRead)
        begin
            read_data_1 = registers[rs];
            read_data_2 = registers[rt];
        end
    end
endmodule

uPower/Code/Read_Memory.v
module read_data_memory (
    output reg [63:0] read_data,
    input [63:0] address, 
    input [63:0] write_data,
    input [5:0] opcode, 
    input MemWrite, MemRead
);

    reg [63:0] data_mem [255:0];

    initial
    begin
        $readmemb("data.mem", data_mem, 5, 0);
    end

    always @ (address) 
    begin
        if(MemWrite) 
        begin
            if(opcode == 6'd38)     
            begin
                data_mem[address] = {{56{1'b0}}, write_data[7:0]};
            end

            else if(opcode == 6'd44) 
            begin
                data_mem[address] = {{48{1'b0}}, write_data[7:0]};
            end
            
            else if(opcode == 6'd36) begin
                data_mem[address] = {{32{1'b0}}, write_data[7:0]};
            end
            
            else 
            begin
                data_mem[address] = write_data;
            end
            // Write the updated contents back to the data_mem file
            $writememb("data.mem", data_mem);            
        end

    end
endmodule

uPower/Code/ALU64Bit.v
/* Module designed to act as the ALU - takes in the opcode, contents of the registers, shiftAmount, ALUResult and AluSrc signals
   with the signedImm as arguments
*/

module ALU64bit(
    output reg [63:0] ALU_result,
    output reg Branch,
    input [5:0] opcode,
    input [4:0] rs, rt, bo, bi,
    input [15:0] si,
    input [13:0] ds, 
    input [9:0] xox,
    input [8:0] xoxo,
    input aa, 
    input [1:0] xods);

    reg signed [63:0] temp, signed_rt, signed_rs;
    reg [63:0] zeroExtendSI, signExtendSI, zeroExtendDS;

    always @(rs, rt, si, xoxo, xox, xods, bo, bi, aa, ds)
    begin

      signed_rs = rs;
      signed_rt = rt;
      zeroExtendSI = {{48{1'b0}},si[15:0]};
      signExtendSI = {{48{si[15]}},si[15:0]};
      zeroExtendDS = {{50{1'b0}},ds[13:0]};

      if(opcode == 6'd31 & xoxo != 9'd0)    //XO Format
      begin
          
          case(xoxo)

            9'd266: //ADD
                ALU_result = signed_rs + signed_rt;
            9'd40 : //SUBF
                ALU_result = signed_rt - signed_rs;
          endcase
      end  

      else if(opcode == 6'd31 & xox != 10'd0)   //X Format
      begin

        case(xox)

            10'd28: //AND
                ALU_result = rt & rs;
            10'd476: //NAND
                ALU_result = ~(rs & rt);
            10'd444: //OR
                ALU_result = rs | rt;
            10'd316: //XOR
                ALU_result = rs ^ rt;
            10'd986: //EXTSW
                ALU_result = {{32{rt[31]}}, rt[31:0]};
        endcase
      end

      else if(opcode == 6'd19)      //B Format 
      begin
        if(aa == 1) //BEQ
        begin
          ALU_result = signed_rs - signed_rt;
          if(ALU_result == 0)
              Branch = 1'b1;
          else
              Branch = 1'b0;
        end
        else if(aa == 0) //BNE
        begin
            ALU_result = signed_rs - signed_rt;
            if(ALU_result != 0)
            begin
              Branch = 1'b1;
              ALU_result = 1'b0;
              end
            else
              Branch = 1'b0; 
        end
      end

      else if(opcode == 6'd18) //I Format
            Branch = 1'b1;
    
      else if(si != 15'b0)      //D Format
      begin
          case(opcode)

            6'd14: //ADDI
                ALU_result = rt + zeroExtendSI;
            6'd15: //ADDIS
                ALU_result = rt + signExtendSI;
            6'd28: //ANDI
                ALU_result = rt & zeroExtendSI;
            6'd24: //ORI
                ALU_result = rt | zeroExtendSI;
            6'd26: //XORI
                ALU_result = rt ^ zeroExtendSI;
            6'd32: //LW0
                ALU_result = rt + zeroExtendSI;
            6'd36: //SW
                ALU_result = rt + signExtendSI;
            6'd37: //SWU
                ALU_result = rt + signExtendSI;
            6'd40: //LHW
                ALU_result = rt + signExtendSI;
            6'd42: //LHWA
                ALU_result = rt + signExtendSI;
            6'd44: //SHW
                ALU_result = rt + signExtendSI;
            6'd34: //LB0    
                ALU_result = rt + zeroExtendSI;
            6'd38: //SB
                ALU_result = rt + signExtendSI;
          endcase
      end  

      else if(ds != 14'b0)      //DS Format
      begin
        if(opcode == 6'd58)
            ALU_result = rt + zeroExtendDS;
        else if(opcode == 6'd62)
            ALU_result = rt + zeroExtendDS;  
      end
    end

    //Display
    initial 
    begin
        $monitor("Opcode : %6b, RS : %64b, RT : %64b, signExtendSI = %64b, zeroExtendSI = %64b, zeroExtendDS = %64b, Result : %64b\n",
        opcode, rs, rt, signExtendSI, zeroExtendSI, zeroExtendDS, ALU_result);
    end
	
endmodule

uPower/Code/Control_Unit.v
`timescale 1ns/1ns
/* Module to behave like the control unit to set the necessary signals for the execution of an 
   instruction -
   1. RegDst - Which field of the instruction is the register to be written to
   2. RegWrite - Write to register file
   3. RegRead - Read from a register
   4. ALUSrc - The source for the second input to the ALU
   5. PCSrc - Source for PC (next instruction to be executed)
   6. MemRead - Read from the main memory
   7. MemWrite - Write to the main memory
   8. MemToReg - Source of write_data (data to be written to the register file)
   9. Branch -  When a branch/jump instruction is used
*/

module control_unit(
    output reg  RegRead,
                RegWrite,
                MemRead,
                MemWrite,
                Branch,
    input [5:0] opcode,
    input [9:0] xox,
    input [8:0] xoxo, 
    input [1:0] xods
);

    // always @(opcode, xoxo, xox, xods)
    // begin
    //     MemRead = 1'b0;
    //     MemWrite = 1'b0;
    //     RegRead = 1'b0;
    //     RegWrite = 1'b0;
    //     Branch = 1'b0;
    // end
    
    always @(opcode, xoxo, xox, xods)
    begin
        MemRead = 1'b0;
        MemWrite = 1'b0;
        RegRead = 1'b0;
        RegWrite = 1'b0;
        Branch = 1'b0;
        //X OR XO Format
        if(opcode == 6'd31) 
        begin
            RegRead = 1'b1;
            RegWrite = 1'b1;
        end

        //D Format - ALU Only 
        else if(opcode == 6'd14 | opcode == 6'd15 |opcode == 6'd28 |opcode == 6'd24 |opcode == 6'd26)
        begin
            RegRead = 1'b1;
            RegWrite = 1'b1;
        end

        //D Format Loads and DS load
        else if(opcode == 6'd58 | opcode == 6'd32 |opcode == 6'd40 |opcode == 6'd42 |opcode == 6'd34)
        begin
            RegRead = 1'b1;
            RegWrite = 1'b1;
            MemRead = 1'b1;
        end

        //D-Format Stores and DS Store
        else if(opcode == 6'd38 |opcode == 6'd44 |opcode == 6'd37 |opcode == 6'd36 |opcode == 6'd62)
        begin
            RegRead = 1'b1;
            MemWrite = 1'b1;
        end

        //Unconditonal Branch
        else if(opcode == 6'd18)
        begin
            Branch = 1'b1;
        end

        //Conditional Branch
        else if(opcode == 6'd19)
        begin
            Branch = 1'b1;
            RegRead = 1'b1;
        end
    end
endmodule

module control_unit_tb();
    wire RegRead, RegWrite, MemRead, MemWrite, Branch;
    reg [5:0] opcode;
    reg [9:0] xox;
    reg [8:0] xoxo; 
    reg [1:0] xods;

    control_unit controller(
        .RegRead(RegRead),
        .RegWrite(RegWrite),
        .MemRead(MemRead),
        .MemWrite(MemWrite),
        .Branch(Branch),
        .opcode(opcode),
        .xox(xox),
        .xoxo(xoxo),
        .xods(xods)
    );

    initial begin
        //add - XO
        opcode = 6'd31;
        xoxo = 9'd266;
        #10;

        //ld - DS
        opcode = 6'd58;
        xods = 2'd0;
        #10;
        
        //ba - I
        opcode = 6'd18;
        #10;
        
        //and - X
        opcode = 6'd31;
        xox = 10'd28;
        #10;
        
        //bc - B
        opcode = 6'd19;
        #10;
        
        //bl - I
        opcode = 6'd18;
        #10;
        
        //xori - D
        opcode = 6'd26;
        #10;
        
    end

    initial begin
        $dumpfile("control_unit_tb.vcd");
        $dumpvars(0,control_unit_tb);
    end
endmodule

uPower/Code/Instruction_parse.v
/* Module designed to read the instruction and assign the various
   components of the instruction to suitable variables depending on the format
*/

module ins_parse(
    output wire [5:0] opcode, 
    output reg [4:0] rs, rt, rd, bo, bi, 
    output reg aa, lk, rc, oe,
    output reg [9:0] xox,
    output reg [8:0] xoxo, 
    output reg [15:0] si, 
    output reg [13:0] bd, ds,
    output reg [1:0] xods, 
    output reg [23:0] li,
    input [31:0] instruction, p_count
);

    assign opcode = instruction[31:26];

    always @(instruction) 
    begin

        //XO
        if(opcode == 6'd31 & (instruction[9:1] == 9'd266 | instruction[9:1] == 9'd40))
        begin
            rd = instruction[25:21];
            rt = instruction[20:16];
            rs = instruction[15:11];
            oe = instruction[10];
            xoxo = instruction[9:1];
            rc = instruction[0];
        end

        //X
        else if(opcode == 6'd31)
        begin
            rd = instruction[25:21];
            rt = instruction[20:16];
            rs = instruction[15:11];
            xox = instruction[10:1];
            rc = instruction[0];
        end

        //D
        else if(opcode == 6'd14 | opcode == 6'd15 | opcode == 6'd28 | opcode == 6'd24 | opcode == 6'd26 | opcode == 6'd32 | opcode == 6'd36 | opcode == 6'd37 |opcode == 6'd40 | opcode == 6'd42 |opcode == 6'd44 |opcode == 6'd34 |opcode == 6'd38)
        begin
            rd = instruction[25:21];
            rt = instruction[20:16];   
            si = instruction[15:0];
        end

        //B
        else if(opcode == 6'd19)
        begin
            bo = instruction[25:21];
            bi = instruction[20:16];
            bd = instruction[15:2];
            aa = instruction[1];
            lk = instruction[0];
        end

        //I
        else if(opcode == 6'd18)
        begin
            li = instruction[25:2];
            aa = instruction[1];
            lk = instruction[0];
        end

        //DS
        else
        begin
            rd = instruction[25:21];
            rt = instruction[20:16];
            ds = instruction[15:2];
            xods = instruction[1:0];
        end
    end
endmodule

uPower/Code/Read_Instructions.v
/* Test Module designed to read the instructions from a .mem file containing the 32-bit uPower instructions
   in binary
*/

module read_instructions(instruction, program_counter);

    input [31:0] program_counter;
    output reg [31:0] instruction;

    reg [31:0] instructions [5:0];     //set to the number of instructions in the file

    initial begin
        $readmemb("instructions.mem", instructions, 5, 0);
    end

    always @ (program_counter) begin
        instruction = instructions[program_counter];
    end

endmodule

uPower/Testbenches/uPowerISA_Core.v
/* uPowerISA Core Module is the centre of all operations that handles all the operations and instantiates
all the necessary modules
*/

`include "Control_Unit.v"
`include "Instruction_parse.v"
`include "ALU64Bit.v"
`include "Read_Instructions.v"
`include "Read_Memory.v"
`include "Read_Registers.v"

module uPower_core(clock);

input clock; //Execution happens only at positive level-transition (edge sensitive)

//Program counter

reg [31:0] PC = 32'b0;

//Instruction
wire [31:0] instruction;

//Parse instruction
wire [5:0] opcode;
wire [4:0] rs,rt,rd,bo,bi;
wire [8:0] xoxo;
wire [9:0] xox;
wire rc,aa,lk,oe;
wire [13:0] bd,ds;
wire [15:0] si;
wire [23:0] li;
wire [1:0] xods;

//Signals

wire RegRead, RegWrite, RegDst, MemRead, MemWrite, Branch;

//Register contents
wire [63:0] write_data, rs_content, rt_content, memory_read_data;

//Instantiating all necessary modules
read_instructions InstructionMemory(instruction, PC);

ins_parse Parse(opcode, rs, rt, rd, bo, bi, aa, lk, rc, oe, xox, xoxo, si, bd, ds, xods, li, instruction, PC);

control_unit Signals(RegRead, RegWrite, MemRead, MemWrite, Branch, opcode, xox, xoxo, xods);

ALU64bit ALU(write_data, Branch, opcode, rs, rt, bo, bi, si, ds, xox, xoxo, aa, xods);

read_data_memory MainMemory(memory_read_data, write_data, rs_content, opcode, MemWrite, MemRead);

read_registers Registers(rs_content, rt_content,  write_data, rs, rt, rd, opcode, RegRead, RegWrite, RegDst, clock);

// PC operations - The next instruction is read only when the clock is at positive edge

always @(posedge clock)
 begin
     if(opcode == 6'd18)
       PC = {{8{1'b0}},li};
     else if(write_data == 0 & Branch == 1)
       PC = PC + 1 + $signed(bd);
     else
       PC = PC +1 ;
 end

endmodule

uPower/Code/uPowerISA_tb.v
// uPowerISA test bench - To drive and simulate the entire MIPS ALU 

`include "uPowerISA_Core.v"

module uPower_testbench();

reg clock;
wire result;

uPower_core test(clock);
initial clock = 0;

initial 
 begin
#100 clock=~clock; #100 clock=~clock;
#100 clock=~clock; #100 clock=~clock;
#100 clock=~clock;
 end

initial begin
  $dumpfile("uPower_testbench.vcd"); 
  $dumpvars(0, uPower_testbench);
end

endmodule

uPower/VCD Files/uPower_testbench.vcd
$date
	Sun May 17 20:28:13 2020
$end
$version
	Icarus Verilog
$end
$timescale
	1s
$end
$scope module uPower_testbench $end
$var reg 1 ! clock $end
$scope module test $end
$var wire 1 " Branch $end
$var wire 1 # RegDst $end
$var wire 1 ! clock $end
$var wire 9 $ xoxo [8:0] $end
$var wire 10 % xox [9:0] $end
$var wire 2 & xods [1:0] $end
$var wire 64 ' write_data [63:0] $end
$var wire 16 ( si [15:0] $end
$var wire 64 ) rt_content [63:0] $end
$var wire 5 * rt [4:0] $end
$var wire 64 + rs_content [63:0] $end
$var wire 5 , rs [4:0] $end
$var wire 5 - rd [4:0] $end
$var wire 1 . rc $end
$var wire 6 / opcode [5:0] $end
$var wire 1 0 oe $end
$var wire 64 1 memory_read_data [63:0] $end
$var wire 1 2 lk $end
$var wire 24 3 li [23:0] $end
$var wire 32 4 instruction [31:0] $end
$var wire 14 5 ds [13:0] $end
$var wire 5 6 bo [4:0] $end
$var wire 5 7 bi [4:0] $end
$var wire 14 8 bd [13:0] $end
$var wire 1 9 aa $end
$var wire 1 : RegWrite $end
$var wire 1 ; RegRead $end
$var wire 1 < MemWrite $end
$var wire 1 = MemRead $end
$var reg 32 > PC [31:0] $end
$scope module ALU $end
$var wire 9 ? xoxo [8:0] $end
$var wire 10 @ xox [9:0] $end
$var wire 2 A xods [1:0] $end
$var wire 16 B si [15:0] $end
$var wire 5 C rt [4:0] $end
$var wire 5 D rs [4:0] $end
$var wire 6 E opcode [5:0] $end
$var wire 14 F ds [13:0] $end
$var wire 5 G bo [4:0] $end
$var wire 5 H bi [4:0] $end
$var wire 1 9 aa $end
$var reg 64 I ALU_result [63:0] $end
$var reg 1 J Branch $end
$var reg 64 K signExtendSI [63:0] $end
$var reg 64 L signed_rs [63:0] $end
$var reg 64 M signed_rt [63:0] $end
$var reg 64 N zeroExtendDS [63:0] $end
$var reg 64 O zeroExtendSI [63:0] $end
$upscope $end
$scope module InstructionMemory $end
$var wire 32 P program_counter [31:0] $end
$var reg 32 Q instruction [31:0] $end
$upscope $end
$scope module MainMemory $end
$var wire 64 R address [63:0] $end
$var wire 64 S write_data [63:0] $end
$var wire 6 T opcode [5:0] $end
$var wire 1 < MemWrite $end
$var wire 1 = MemRead $end
$var reg 64 U read_data [63:0] $end
$upscope $end
$scope module Parse $end
$var wire 32 V instruction [31:0] $end
$var wire 32 W p_count [31:0] $end
$var wire 6 X opcode [5:0] $end
$var reg 1 9 aa $end
$var reg 14 Y bd [13:0] $end
$var reg 5 Z bi [4:0] $end
$var reg 5 [ bo [4:0] $end
$var reg 14 \ ds [13:0] $end
$var reg 24 ] li [23:0] $end
$var reg 1 2 lk $end
$var reg 1 0 oe $end
$var reg 1 . rc $end
$var reg 5 ^ rd [4:0] $end
$var reg 5 _ rs [4:0] $end
$var reg 5 ` rt [4:0] $end
$var reg 16 a si [15:0] $end
$var reg 2 b xods [1:0] $end
$var reg 10 c xox [9:0] $end
$var reg 9 d xoxo [8:0] $end
$upscope $end
$scope module Registers $end
$var wire 1 # RegDst $end
$var wire 1 ! clk $end
$var wire 6 e opcode [5:0] $end
$var wire 5 f rd [4:0] $end
$var wire 5 g rs [4:0] $end
$var wire 5 h rt [4:0] $end
$var wire 64 i write_data [63:0] $end
$var wire 1 : RegWrite $end
$var wire 1 ; RegRead $end
$var reg 64 j read_data_1 [63:0] $end
$var reg 64 k read_data_2 [63:0] $end
$upscope $end
$scope module Signals $end
$var wire 6 l opcode [5:0] $end
$var wire 2 m xods [1:0] $end
$var wire 10 n xox [9:0] $end
$var wire 9 o xoxo [8:0] $end
$var reg 1 p Branch $end
$var reg 1 = MemRead $end
$var reg 1 < MemWrite $end
$var reg 1 ; RegRead $end
$var reg 1 : RegWrite $end
$upscope $end
$upscope $end
$upscope $end
$enddefinitions $end
#0
$dumpvars
0p
bx o
bx n
bx m
b101010 l
bx k
bx j
b100100100111100 i
b10010 h
bx g
b1010 f
b101010 e
bx d
bx c
bx b
b100100100101010 a
b10010 `
bx _
b1010 ^
bx ]
bx \
bx [
bx Z
bx Y
b101010 X
b0 W
b10101001010100100100100100101010 V
bx U
b101010 T
bx S
b100100100111100 R
b10101001010100100100100100101010 Q
b0 P
b100100100101010 O
b0xxxxxxxxxxxxxx N
b10010 M
b0xxxxx L
b100100100101010 K
xJ
b100100100111100 I
bx H
bx G
bx F
b101010 E
bx D
b10010 C
b100100100101010 B
bx A
bx @
bx ?
b0 >
1=
0<
1;
1:
x9
bx 8
bx 7
bx 6
bx 5
b10101001010100100100100100101010 4
bx 3
x2
bx 1
x0
b101010 /
x.
b1010 -
bx ,
bx +
b10010 *
bx )
b100100100101010 (
b100100100111100 '
bx &
bx %
bx $
z#
x"
0!
$end
#100
b1001001001010 N
b1010 M
0:
0;
0=
b10 &
b10 A
b10 b
b10 m
b1001001001010 5
b1001001001010 F
b1001001001010 \
b1010 *
b1010 C
b1010 `
b1010 h
b10010 -
b10010 ^
b10010 f
b10100 /
b10100 E
b10100 T
b10100 X
b10100 e
b10100 l
b1010010010010100100100100101010 4
b1010010010010100100100100101010 Q
b1010010010010100100100100101010 V
b1 >
b1 P
b1 W
1!
#200
0!
#300
b1111111111111111111111111111111111111111111111111001001001010100 '
b1111111111111111111111111111111111111111111111111001001001010100 I
b1111111111111111111111111111111111111111111111111001001001010100 R
b1111111111111111111111111111111111111111111111111001001001010100 i
b1111111111111111111111111111111111111111111111111001001001001010 K
b1001001001001010 O
1<
1;
b1001001001001010 (
b1001001001001010 B
b1001001001001010 a
b100100 /
b100100 E
b100100 T
b100100 X
b100100 e
b100100 l
b10010010010010101001001001001010 4
b10010010010010101001001001001010 Q
b10010010010010101001001001001010 V
b10 >
b10 P
b10 W
1!
#400
0!
#500
1J
0;
0<
0p
02
19
b100101001001100111101101 3
b100101001001100111101101 ]
b10010 /
b10010 E
b10010 T
b10010 X
b10010 e
b10010 l
b1001010010100100110011110110110 4
b1001010010100100110011110110110 Q
b1001010010100100110011110110110 V
b11 >
b11 P
b11 W
1!
#600
0!
#700
b0xxxxxxxxxxxxxx N
b0xxxxx M
bx &
bx A
bx b
bx m
bx 5
bx F
bx \
bx *
bx C
bx `
bx h
bx -
bx ^
bx f
bx /
bx E
bx T
bx X
bx e
bx l
bx 4
bx Q
bx V
b100101001001100111101101 >
b100101001001100111101101 P
b100101001001100111101101 W
1!
#800
0!
#900
b100101001001100111101110 >
b100101001001100111101110 P
b100101001001100111101110 W
1!
#1000
0!
#1100
b100101001001100111101111 >
b100101001001100111101111 P
b100101001001100111101111 W
1!
#1200
0!
#1300
b100101001001100111110000 >
b100101001001100111110000 P
b100101001001100111110000 W
1!
#1400
0!
#1500
b100101001001100111110001 >
b100101001001100111110001 P
b100101001001100111110001 W
1!
#1600
0!
#1700
b100101001001100111110010 >
b100101001001100111110010 P
b100101001001100111110010 W
1!
